xmlconfig/setup.py
xmlconfig/__init__.py
xmlconfig-0.0.3.data/scripts/xmlconfig
xmlconfig-0.0.3.dist-info/DESCRIPTION.rst
xmlconfig-0.0.3.dist-info/METADATA
xmlconfig-0.0.3.dist-info/top_level.txt
xmlconfig-0.0.3.dist-info/WHEEL
xmlconfig-0.0.3.dist-info/RECORD
xmlconfig-0.0.3.dist-info/metadata.json
