Metadata-Version: 2.0
Name: xmlconfig
Version: 0.0.3
Summary: XML config helper
Home-page: http://github.com/gutomaia/xmlconfig/
Author: Gustavo Maia Neto (Guto Maia)
Author-email: guto@guto.net
License: GPL3
Platform: UNKNOWN
Classifier: Development Status :: 3 - Alpha
Classifier: Environment :: Console
